{
    "type": "flex",
    "altText": "ติดต่อ / contact",
    "contents": {
  "type": "bubble",
  "body": {
    "type": "box",
    "layout": "vertical",
    "spacing": "md",
    "contents": [
      {
        "type": "box",
        "layout": "vertical",
        "contents": [
          {
            "type": "image",
            "url": "https://www.viicheck.com/img/logo/VII-check-LOGO-W-v3.png",
            "size": "4xl",
            "aspectRatio": "16:9",
            "aspectMode": "fit",
            "action": {
              "type": "uri",
              "label": "action",
              "uri": "https://www.viicheck.com/"
            }
          },
          {
            "type": "image",
            "url": "https://www.viicheck.com/img/stickerline/PNG/1.png",
            "size": "full",
            "aspectRatio": "16:9",
            "align": "center",
            "aspectMode": "fit",
            "offsetBottom": "md"
          }
        ]
      },
      {
        "type": "box",
        "layout": "vertical",
        "spacing": "sm",
        "contents": [
          {
            "type": "separator",
            "margin": "xl",
            "color": "#ff0101"
          },
          {
            "type": "box",
            "layout": "baseline",
            "contents": [
              {
                "type": "icon",
                "url": "https://www.viicheck.com/img/icon/car.png",
                "size": "3xl",
                "margin": "none",
                "offsetTop": "md"
              },
              {
                "type": "text",
                "text": "โปรโมชั่นรถยนต์",
                "margin": "xl",
                "action": {
                  "type": "message",
                  "label": "โปรโมชั่นรถยนต์",
                  "text": "โปรโมชั่นรถยนต์"
                },
                "weight": "bold",
                "flex": 4
              },
              {
                "type": "text",
                "text": ">>>",
                "size": "sm",
                "align": "end",
                "color": "#ff0101",
                "action": {
                  "type": "message",
                  "label": "โปรโมชั่นรถยนต์",
                  "text": "โปรโมชั่นรถยนต์"
                }
              }
            ],
            "height": "50px",
            "action": {
              "type": "message",
              "label": "โปรโมชั่นรถยนต์",
              "text": "โปรโมชั่นรถยนต์"
            },
            "margin": "md"
          },
          {
            "type": "separator",
            "margin": "xl",
            "color": "#ff0101"
          },
          {
            "type": "box",
            "layout": "baseline",
            "contents": [
              {
                "type": "icon",
                "url": "https://www.viicheck.com/img/icon/motorcycle.png",
                "size": "3xl",
                "margin": "none",
                "offsetTop": "md"
              },
              {
                "type": "text",
                "text": "โปรโมชั่นรถจักรยานยนต์",
                "weight": "bold",
                "margin": "xl",
                "action": {
                  "type": "message",
                  "label": "โปรโมชั่นรถจักรยานยนต์",
                  "text": "โปรโมชั่นรถจักรยานยนต์"
                },
                "flex": 4
              },
              {
                "type": "text",
                "text": ">>>",
                "size": "sm",
                "align": "end",
                "color": "#ff0101",
                "action": {
                  "type": "message",
                  "label": "โปรโมชั่นรถจักรยานยนต์",
                  "text": "โปรโมชั่นรถจักรยานยนต์"
                }
              }
            ],
            "height": "50px",
            "action": {
              "type": "message",
              "label": "โปรโมชั่นรถจักรยานยนต์",
              "text": "โปรโมชั่นรถจักรยานยนต์"
            }
          },
          {
            "type": "separator",
            "margin": "xl",
            "color": "#ff0101"
          }
        ],
        "offsetBottom": "md"
      }
    ],
    "borderWidth": "bold",
    "cornerRadius": "xl",
    "borderColor": "#ff0101"
  },
  "styles": {
    "hero": {
      "backgroundColor": "#ff0101"
    }
  }
}
}